README.md
setup.py
bcikit/__init__.py
bcikit.egg-info/PKG-INFO
bcikit.egg-info/SOURCES.txt
bcikit.egg-info/dependency_links.txt
bcikit.egg-info/requires.txt
bcikit.egg-info/top_level.txt
bcikit/datasets/EEGDataloader.py
bcikit/datasets/EEGDataset.py
bcikit/datasets/__init__.py
bcikit/datasets/ssvep/__init__.py
bcikit/datasets/ssvep/hsssvep.py
bcikit/models/__init__.py
bcikit/models/EEGNet/CompactEEGNet.py
bcikit/models/EEGNet/__init__.py
bcikit/models/common/__init__.py
bcikit/models/common/conv.py
bcikit/models/common/utils.py