Metadata-Version: 2.1
Name: bcikit
Version: 0.0.1.dev1
Summary: A toolbox for data manipulation and transformation for EEG and machine learning.
Home-page: https://github.com/ntubci/bcikit
Author: NTU Brain-Computing Research
Author-email: ntuscsebci@gmail.com
License: UNKNOWN
Project-URL: Source, https://github.com/ntubci/bcikit
Project-URL: Documentation, https://bcikit.readthedocs.io
Project-URL: Tracker, https://github.com/ntubci/bcikit/issues
Platform: UNKNOWN
Classifier: Programming Language :: Python :: 3
Classifier: License :: OSI Approved :: Apache Software License
Classifier: Operating System :: OS Independent
Requires-Python: >=3.3
